[
    {
      "id": "AML001",
      "name": "Anartz",
      "lastname": "Mugika Ledo",
      "birthday": "10/01/1986",
      "phone": 373827222,
      "address": "Ezozia, 20590 Soraluze (Gipuzkoa)",
      "position": "PFS",
      "status": 1
    },
    {
      "id": "MNU001",
      "name": "Mikel",
      "lastname": "Narbaiza Urizar",
      "birthday": "20/02/1980",
      "phone": 333333333,
      "address": "Untzaga, 20600, Eibar (Gipuzkoa)",
      "position": "FRO",
      "status": 2
    }
  ]